{
  "metadata": {
    "broker": "J Thomas & Company Private Limited",
    "auction_centre": "Kolkata",
    "country": "India",
    "currency": "INR",
    "sale_number": 32,
    "week_number": 32,
    "year": 2025,
    "sale_date_start": "2025-08-12",
    "sale_date_end": "2025-08-13"
  },
  "commentary": {
    "CTC": {
      "market": "Good demand. Liquoring Assams tended irregularly easier. Mediums sold around last levels. Medium and plainer Dooars sold at irregularly easier levels.",
      "buying": "Hindustan Unilever: Operated. TCPL: Selective. Western India: Operated. Exporters: Fair enquiry. Other Packeteers: Good Support."
    },
    "DUST": {
      "market": "Good demand. All sorts irregularly easier.",
      "buying": "Hindustan Unilever: Operated. TCPL: Selective. Western India: Operated. Exporters: Fair enquiry. Other Packeteers: Good Support."
    },
    "Orthodox": {
      "market": "Strong demand. Nominal quantity of tippy teas sold readily. Clean well made Whole Leaf and Brokens sold at fully firm rates. Remainder Whole Leaf and Brokens regular around last. Fannings and Cleaner Secondaries sold around last levels.",
      "buying": "Middle East: Active. CIS: Good Support. Hindustan Unilever: Very Selective. Western India: Supported the better teas."
    },
    "Darjeeling": {
      "market": "Good demand but at lower levels to last week. High elevation whole leaf sold at easier levels as compared to last week. Brokens and Fannings followed a similar trend. Plainer whole leaf similarly sold at lower levels with some outlots being witnessed.",
      "buying": "Hindustan Unilever: Active. Exporters: Good support. Teloijan: Mainstay."
    }
  },
  "statistical_summaries": {
    "auction_averages_comparison": [
      {
        "category": "CTC LEAF",
        "current_sale_avg_25_26": 230.74,
        "previous_sale_avg_25_26": 239.16,
        "diff_25_26": -8.42,
        "ytd_avg_25_26": 236.87,
        "ytd_avg_24_25": 266.5,
        "ytd_avg_23_24": 221.27
      },
      {
        "category": "DUST",
        "current_sale_avg_25_26": 251.63,
        "previous_sale_avg_25_26": 260.12,
        "diff_25_26": -8.48,
        "ytd_avg_25_26": 271.52,
        "ytd_avg_24_25": 275.29,
        "ytd_avg_23_24": 224.04
      },
      {
        "category": "TOTAL",
        "current_sale_avg_25_26": 238.21,
        "previous_sale_avg_25_26": 247.42,
        "diff_25_26": -9.21,
        "ytd_avg_25_26": 249.29,
        "ytd_avg_24_25": 269.92,
        "ytd_avg_23_24": 222.13
      },
      {
        "category": "ORTHODOX",
        "current_sale_avg_25_26": 321.42,
        "previous_sale_avg_25_26": 316.16,
        "diff_25_26": 5.26,
        "ytd_avg_25_26": 308.42,
        "ytd_avg_24_25": 302.7,
        "ytd_avg_23_24": 224.31
      },
      {
        "category": "DARJEELING",
        "current_sale_avg_25_26": 529.38,
        "previous_sale_avg_25_26": 549.57,
        "diff_25_26": -20.19,
        "ytd_avg_25_26": 556.84,
        "ytd_avg_24_25": 483.86,
        "ytd_avg_23_24": 450.48
      },
      {
        "category": "ALL TEAS",
        "current_sale_avg_25_26": 267.78,
        "previous_sale_avg_25_26": 272.66,
        "diff_25_26": -4.88,
        "ytd_avg_25_26": 273.11,
        "ytd_avg_24_25": 282.35,
        "ytd_avg_23_24": 225.37
      }
    ],
    "offer_sold_statistics": {
      "CTC_Dust": [
        {
          "Grade": "BROKENS",
          "This_Sale": {
            "Offered": 1896801.0,
            "Sold": 1288542.0,
            "Average": 234.98,
            "Out_Percent": 32.0
          },
          "Last_Sale": {
            "Offered": 1808779.0,
            "Sold": 1124552.0,
            "Average": 240.76,
            "Out_Percent": 38.0
          },
          "To_Date": {
            "Offered": 20014860.0,
            "Sold": 13568234.0,
            "Average": 239.26,
            "Out_Percent": 32.0
          }
        },
        {
          "Grade": "FANNINGS",
          "This_Sale": {
            "Offered": 745223.0,
            "Sold": 482023.0,
            "Average": 232.8,
            "Out_Percent": 35.0
          },
          "Last_Sale": {
            "Offered": 670020.0,
            "Sold": 402108.0,
            "Average": 247.67,
            "Out_Percent": 40.0
          },
          "To_Date": {
            "Offered": 6782195.0,
            "Sold": 4503648.0,
            "Average": 242.06,
            "Out_Percent": 34.0
          }
        },
        {
          "Grade": "LEAF SEC.",
          "This_Sale": {
            "Offered": 211046.0,
            "Sold": 173706.0,
            "Average": 193.6,
            "Out_Percent": 18.0
          },
          "Last_Sale": {
            "Offered": 165013.0,
            "Sold": 133381.0,
            "Average": 199.96,
            "Out_Percent": 19.0
          },
          "To_Date": {
            "Offered": 1918386.0,
            "Sold": 1556221.0,
            "Average": 200.98,
            "Out_Percent": 19.0
          }
        },
        {
          "Grade": "LEAF TOTAL",
          "This_Sale": {
            "Offered": 2853069.5,
            "Sold": 1944270.6,
            "Average": 230.74,
            "Out_Percent": 32.0
          },
          "Last_Sale": {
            "Offered": 2643811.9,
            "Sold": 1660040.7,
            "Average": 239.16,
            "Out_Percent": 37.0
          },
          "To_Date": {
            "Offered": 28715440.3,
            "Sold": 19628102.3,
            "Average": 236.87,
            "Out_Percent": 32.0
          }
        },
        {
          "Grade": "DUST",
          "This_Sale": {
            "Offered": 1233056.0,
            "Sold": 908705.0,
            "Average": 260.79,
            "Out_Percent": 26.0
          },
          "Last_Sale": {
            "Offered": 1237088.0,
            "Sold": 903028.0,
            "Average": 273.59,
            "Out_Percent": 27.0
          },
          "To_Date": {
            "Offered": 12528688.0,
            "Sold": 9428402.0,
            "Average": 280.61,
            "Out_Percent": 25.0
          }
        },
        {
          "Grade": "DUST SEC.",
          "This_Sale": {
            "Offered": 224789.0,
            "Sold": 174156.0,
            "Average": 203.88,
            "Out_Percent": 23.0
          },
          "Last_Sale": {
            "Offered": 248103.0,
            "Sold": 178124.0,
            "Average": 191.81,
            "Out_Percent": 28.0
          },
          "To_Date": {
            "Offered": 1982168.0,
            "Sold": 1542166.0,
            "Average": 215.93,
            "Out_Percent": 22.0
          }
        },
        {
          "Grade": "DUST TOTAL",
          "This_Sale": {
            "Offered": 1457844.6,
            "Sold": 1082861.4,
            "Average": 251.63,
            "Out_Percent": 26.0
          },
          "Last_Sale": {
            "Offered": 1485190.6,
            "Sold": 1081151.6,
            "Average": 260.12,
            "Out_Percent": 27.0
          },
          "To_Date": {
            "Offered": 14510856.2,
            "Sold": 10970568.1,
            "Average": 271.52,
            "Out_Percent": 24.0
          }
        },
        {
          "Grade": "TOTAL",
          "This_Sale": {
            "Offered": 4310914.1,
            "Sold": 3027132.0,
            "Average": 238.21,
            "Out_Percent": 30.0
          },
          "Last_Sale": {
            "Offered": 4129002.5,
            "Sold": 2741192.3,
            "Average": 247.42,
            "Out_Percent": 34.0
          },
          "To_Date": {
            "Offered": 43226296.5,
            "Sold": 30598670.4,
            "Average": 249.29,
            "Out_Percent": 29.0
          }
        }
      ],
      "Orthodox": [
        {
          "Grade": "WHOLE LEAF",
          "This_Sale": {
            "Offered": 734036.0,
            "Sold": 682586.0,
            "Average": 347.35,
            "Out_Percent": 7.0
          },
          "Last_Sale": {
            "Offered": 652368.0,
            "Sold": 613859.0,
            "Average": 344.25,
            "Out_Percent": 6.0
          },
          "To_Date": {
            "Offered": 8524925.0,
            "Sold": 7344267.0,
            "Average": 341.59,
            "Out_Percent": 14.0
          }
        },
        {
          "Grade": "BROKENS",
          "This_Sale": {
            "Offered": 620724.0,
            "Sold": 592919.0,
            "Average": 339.17,
            "Out_Percent": 4.0
          },
          "Last_Sale": {
            "Offered": 543004.0,
            "Sold": 518274.0,
            "Average": 334.9,
            "Out_Percent": 5.0
          },
          "To_Date": {
            "Offered": 7788644.0,
            "Sold": 6506718.0,
            "Average": 330.09,
            "Out_Percent": 16.0
          }
        },
        {
          "Grade": "FANNINGS",
          "This_Sale": {
            "Offered": 110885.0,
            "Sold": 103367.0,
            "Average": 181.2,
            "Out_Percent": 7.0
          },
          "Last_Sale": {
            "Offered": 84857.0,
            "Sold": 77451.0,
            "Average": 176.12,
            "Out_Percent": 9.0
          },
          "To_Date": {
            "Offered": 1440610.0,
            "Sold": 1217418.0,
            "Average": 180.49,
            "Out_Percent": 15.0
          }
        },
        {
          "Grade": "SECONDARY",
          "This_Sale": {
            "Offered": 137618.0,
            "Sold": 127963.0,
            "Average": 214.11,
            "Out_Percent": 7.0
          },
          "Last_Sale": {
            "Offered": 153960.0,
            "Sold": 148878.0,
            "Average": 207.97,
            "Out_Percent": 3.0
          },
          "To_Date": {
            "Offered": 2391240.0,
            "Sold": 2270124.0,
            "Average": 207.56,
            "Out_Percent": 5.0
          }
        },
        {
          "Grade": "ORTH. TOTAL",
          "This_Sale": {
            "Offered": 1603262.4,
            "Sold": 1506833.7,
            "Average": 321.42,
            "Out_Percent": 6.0
          },
          "Last_Sale": {
            "Offered": 1434188.7,
            "Sold": 1358462.5,
            "Average": 316.16,
            "Out_Percent": 5.0
          },
          "To_Date": {
            "Offered": 20145418.9,
            "Sold": 17338526.7,
            "Average": 308.42,
            "Out_Percent": 14.0
          }
        }
      ],
      "Darjeeling": [
        {
          "Grade": "WHOLE LEAF",
          "This_Sale": {
            "Offered": 37310.0,
            "Sold": 24804.0,
            "Average": 625.57,
            "Out_Percent": 34.0
          },
          "Last_Sale": {
            "Offered": 36061.0,
            "Sold": 25108.0,
            "Average": 665.36,
            "Out_Percent": 30.0
          },
          "To_Date": {
            "Offered": 357482.0,
            "Sold": 232322.0,
            "Average": 748.71,
            "Out_Percent": 35.0
          }
        },
        {
          "Grade": "BROKENS",
          "This_Sale": {
            "Offered": 9411.0,
            "Sold": 4893.0,
            "Average": 310.54,
            "Out_Percent": 48.0
          },
          "Last_Sale": {
            "Offered": 9984.0,
            "Sold": 5885.0,
            "Average": 277.31,
            "Out_Percent": 41.0
          },
          "To_Date": {
            "Offered": 132992.0,
            "Sold": 89139.0,
            "Average": 339.95,
            "Out_Percent": 33.0
          }
        },
        {
          "Grade": "FANNINGS",
          "This_Sale": {
            "Offered": 6745.0,
            "Sold": 3461.0,
            "Average": 149.38,
            "Out_Percent": 49.0
          },
          "Last_Sale": {
            "Offered": 10440.0,
            "Sold": 5379.0,
            "Average": 306.95,
            "Out_Percent": 48.0
          },
          "To_Date": {
            "Offered": 168196.0,
            "Sold": 89669.0,
            "Average": 275.31,
            "Out_Percent": 47.0
          }
        },
        {
          "Grade": "DARJ. TOTAL",
          "This_Sale": {
            "Offered": 53466.1,
            "Sold": 33157.7,
            "Average": 529.38,
            "Out_Percent": 38.0
          },
          "Last_Sale": {
            "Offered": 56485.3,
            "Sold": 36372.0,
            "Average": 549.57,
            "Out_Percent": 36.0
          },
          "To_Date": {
            "Offered": 658670.4,
            "Sold": 411129.9,
            "Average": 556.84,
            "Out_Percent": 38.0
          }
        }
      ]
    },
    "price_distribution_analysis": {
      "CTC LEAF": {
        "BELOW 160": {
          "Sale_32": 22.39,
          "Sale_31": 21.66,
          "2025_26": 25.71
        },
        "160-180": {
          "Sale_32": 12.71,
          "Sale_31": 11.5,
          "2025_26": 11.57
        },
        "180-200": {
          "Sale_32": 8.9,
          "Sale_31": 8.87,
          "2025_26": 8.46
        },
        "200-250": {
          "Sale_32": 25.67,
          "Sale_31": 24.04,
          "2025_26": 22.22
        },
        "250-300": {
          "Sale_32": 18.03,
          "Sale_31": 18.0,
          "2025_26": 16.8
        },
        "300-350": {
          "Sale_32": 7.42,
          "Sale_31": 10.29,
          "2025_26": 9.68
        },
        "350-400": {
          "Sale_32": 3.7,
          "Sale_31": 3.98,
          "2025_26": 3.92
        },
        "ABOVE 400": {
          "Sale_32": 1.19,
          "Sale_31": 1.66,
          "2025_26": 1.65
        }
      },
      "DUST": {
        "BELOW 160": {
          "Sale_32": 11.05,
          "Sale_31": 11.03,
          "2025_26": 11.27
        },
        "160-180": {
          "Sale_32": 3.47,
          "Sale_31": 4.1,
          "2025_26": 3.8
        },
        "180-200": {
          "Sale_32": 4.37,
          "Sale_31": 4.6,
          "2025_26": 3.9
        },
        "200-250": {
          "Sale_32": 11.62,
          "Sale_31": 12.61,
          "2025_26": 11.03
        },
        "250-300": {
          "Sale_32": 40.13,
          "Sale_31": 35.07,
          "2025_26": 34.68
        },
        "300-350": {
          "Sale_32": 23.87,
          "Sale_31": 25.98,
          "2025_26": 27.92
        },
        "350-400": {
          "Sale_32": 4.56,
          "Sale_31": 5.44,
          "2025_26": 5.9
        },
        "ABOVE 400": {
          "Sale_32": 0.93,
          "Sale_31": 1.18,
          "2025_26": 1.5
        }
      },
      "ORTHODOX": {
        "BELOW 160": {
          "Sale_32": 7.96,
          "Sale_31": 8.31,
          "2025_26": 8.41
        },
        "160-180": {
          "Sale_32": 4.81,
          "Sale_31": 5.63,
          "2025_26": 5.77
        },
        "180-200": {
          "Sale_32": 6.49,
          "Sale_31": 6.87,
          "2025_26": 7.2
        },
        "200-250": {
          "Sale_32": 11.96,
          "Sale_31": 12.86,
          "2025_26": 14.39
        },
        "250-300": {
          "Sale_32": 13.72,
          "Sale_31": 12.64,
          "2025_26": 14.11
        },
        "300-350": {
          "Sale_32": 19.88,
          "Sale_31": 19.43,
          "2025_26": 18.26
        },
        "350-400": {
          "Sale_32": 16.83,
          "Sale_31": 17.22,
          "2025_26": 14.38
        },
        "400-500": {
          "Sale_32": 13.53,
          "Sale_31": 12.13,
          "2025_26": 11.32
        },
        "500-600": {
          "Sale_32": 3.04,
          "Sale_31": 3.0,
          "2025_26": 3.71
        },
        "ABOVE 600": {
          "Sale_32": 1.78,
          "Sale_31": 1.91,
          "2025_26": 2.44
        }
      }
    }
  }
}